soda_clang/main.py
soda_clang/main_cxx.py
soda_clang-2025.2.3.0.dist-info/METADATA
soda_clang-2025.2.3.0.dist-info/WHEEL
soda_clang-2025.2.3.0.dist-info/entry_points.txt
soda_clang-2025.2.3.0.dist-info/licenses/LICENSE
soda_clang-2025.2.3.0.dist-info/RECORD
